tap_amazon_sqs/__init__.py
tap_amazon_sqs/client.py
tap_amazon_sqs/schemas/message.json
tap_amazon_sqs/streams.py
tap_amazon_sqs/tap.py
tap_amazon_sqs-0.0.1.dist-info/METADATA
tap_amazon_sqs-0.0.1.dist-info/WHEEL
tap_amazon_sqs-0.0.1.dist-info/entry_points.txt
tap_amazon_sqs-0.0.1.dist-info/RECORD
