Metadata-Version: 2.1
Name: tap-amazon-sqs
Version: 0.0.1
Summary: `tap-amazon-sqs` is a Singer tap for amazon-sqs, built with the Meltano Singer SDK.
License: Apache 2.0
Keywords: ELT,amazon-sqs
Author: James Marcogliese
Requires-Python: >=3.7.1,<3.12
Classifier: License :: Other/Proprietary License
Classifier: Programming Language :: Python :: 3
Classifier: Programming Language :: Python :: 3.8
Classifier: Programming Language :: Python :: 3.9
Classifier: Programming Language :: Python :: 3.10
Classifier: Programming Language :: Python :: 3.11
Provides-Extra: s3
Requires-Dist: boto3 (>=1.26.129,<2.0.0)
Requires-Dist: botocore (>=1.29.129,<2.0.0)
Requires-Dist: fs-s3fs (>=1.1.1,<2.0.0) ; extra == "s3"
Requires-Dist: moto (>=4.1.8,<5.0.0)
Requires-Dist: singer-sdk (>=0.26.0,<0.27.0)
